jbank
