Metadata-Version: 2.4
Name: django-jbank
Version: 4.9.1
Summary: Collection of small utilities for Django and Django REST framework projects.
Author-email: Jani Kajala <kajala@gmail.com>
License-Expression: MIT
Project-URL: Homepage, https://github.com/kajala/django-jbank
Project-URL: Issues, https://github.com/kajala/django-jbank/issues
Classifier: Programming Language :: Python :: 3
Classifier: Operating System :: OS Independent
Requires-Python: >=3.8
License-File: LICENSE.txt
Requires-Dist: Django>=3.0.0
Requires-Dist: django-jutil>=4.1.4
Requires-Dist: django-jacc>=3.8.8
Requires-Dist: django-extensions>=2.2.5
Requires-Dist: lxml>=4.6.5
Requires-Dist: cryptography==44.0.1
Requires-Dist: xmlsec==1.3.13
Requires-Dist: zeep==4.2.1
Requires-Dist: schwifty>=2023.11.2
Dynamic: license-file
